{
  "@context": "http://iiif.io/api/presentation/3/context.json",
  "id": "https://tanyaclement.github.io/znh_aviary/annotations/s1576-t86-243-canvas-1-notes.json",
  "type": "AnnotationPage",
  "label": "notes",
  "items": [
    {
      "@context": "http://www.w3.org/ns/anno.jsonld",
      "id": "s1576-t86-243-canvas-1-notes-annotation-0.json",
      "type": "Annotation",
      "motivation": [
        "supplementing",
        "commenting"
      ],
      "body": [
        {
          "type": "TextualBody",
          "value": "[inaudible]",
          "format": "text/plain",
          "purpose": "commenting"
        },
        {
          "type": "TextualBody",
          "value": "Herbert Halpert",
          "format": "text/plain",
          "purpose": "tagging"
        }
      ],
      "target": {
        "source": {
          "id": "https://tanyaclement.github.io/znh_aviary/s1576-t86-243/canvas-1/canvas",
          "type": "Canvas",
          "partOf": [
            {
              "id": "https://tanyaclement.github.io/znh_aviary/s1576-t86-243/manifest.json",
              "type": "Manifest"
            }
          ]
        },
        "selector": {
          "type": "PointSelector",
          "t": "2973.60815"
        }
      }
    }
  ]
}